README.md
setup.py
cowin_api/__init__.py
cowin_api/api.py
cowin_api/base_api.py
cowin_api/constants.py
cowin_api/utils.py
cowin_app_services.egg-info/PKG-INFO
cowin_app_services.egg-info/SOURCES.txt
cowin_app_services.egg-info/dependency_links.txt
cowin_app_services.egg-info/requires.txt
cowin_app_services.egg-info/top_level.txt