Metadata-Version: 2.1
Name: cowin-app-services
Version: 0.0.2
Summary: Python Library for CoWin API
Home-page:  
Author: Taranvir Singh Saini
Author-email: taranvir.554@gmail.com
License: UNKNOWN
Keywords: cowin,covid,vaccine
Platform: UNKNOWN
Classifier: Development Status :: 5 - Production/Stable
Classifier: Environment :: Console
Classifier: License :: OSI Approved :: MIT License
Classifier: Programming Language :: Python :: 3
Classifier: Programming Language :: Python :: 3.6
Classifier: Programming Language :: Python :: 3.7
Classifier: Programming Language :: Python :: 3.8
Classifier: Programming Language :: Python :: 3.9
Classifier: Programming Language :: Python :: 3 :: Only
Requires-Python: >=3.6, <4
